farm/__init__.py
farm/_version.py
farm/eval.py
farm/experiment.py
farm/file_utils.py
farm/infer.py
farm/inference_rest_api.py
farm/train.py
farm/utils.py
farm/conversion/__init__.py
farm/conversion/convert_tf_checkpoint_to_pytorch.py
farm/conversion/transformers.py
farm/data_handler/__init__.py
farm/data_handler/data_silo.py
farm/data_handler/dataloader.py
farm/data_handler/dataset.py
farm/data_handler/input_features.py
farm/data_handler/inputs.py
farm/data_handler/nq_utils.py
farm/data_handler/processor.py
farm/data_handler/samples.py
farm/data_handler/utils.py
farm/evaluation/__init__.py
farm/evaluation/metrics.py
farm/evaluation/msmarco_passage_farm.py
farm/evaluation/msmarco_passage_official.py
farm/evaluation/squad_evaluation.py
farm/modeling/__init__.py
farm/modeling/adaptive_model.py
farm/modeling/biadaptive_model.py
farm/modeling/language_model.py
farm/modeling/optimization.py
farm/modeling/prediction_head.py
farm/modeling/predictions.py
farm/modeling/tokenization.py
farm/modeling/wordembedding_utils.py
farm/visual/__init__.py
farm/visual/ascii/__init__.py
farm/visual/ascii/images.py
farm/visual/ascii/text.py
farm-0.8.0.dist-info/LICENSE
farm-0.8.0.dist-info/METADATA
farm-0.8.0.dist-info/WHEEL
farm-0.8.0.dist-info/top_level.txt
farm-0.8.0.dist-info/RECORD
