Metadata-Version: 2.1
Name: farm
Version: 0.8.0
Summary: Framework for finetuning and evaluating transformer based language models
Home-page: https://github.com/deepset-ai/FARM
Author: Timo Moeller, Malte Pietsch, Branden Chan, Tanay Soni, Bogdan Kostic, Julian Risch
Author-email: timo.moeller@deepset.ai
License: Apache
Download-URL: https://github.com/deepset-ai/FARM/archive/v0.8.0.tar.gz
Keywords: BERT NLP deep-learning language-model transformer qa question-answering transfer-learning
Platform: UNKNOWN
Classifier: Intended Audience :: Science/Research
Classifier: License :: OSI Approved :: Apache Software License
Classifier: Programming Language :: Python :: 3
Classifier: Topic :: Scientific/Engineering :: Artificial Intelligence
Requires-Python: >=3.6.0
Requires-Dist: setuptools
Requires-Dist: wheel
Requires-Dist: torch (<1.9,>1.5)
Requires-Dist: tqdm
Requires-Dist: boto3
Requires-Dist: requests
Requires-Dist: scipy (>=1.3.2)
Requires-Dist: sklearn
Requires-Dist: seqeval
Requires-Dist: mlflow (<=1.13.1)
Requires-Dist: transformers (==4.6.1)
Requires-Dist: dotmap
Requires-Dist: Werkzeug (==0.16.1)
Requires-Dist: flask
Requires-Dist: flask-restplus
Requires-Dist: flask-cors
Requires-Dist: dill
Requires-Dist: psutil
Requires-Dist: sentencepiece
Provides-Extra: fasttext
Requires-Dist: fasttext (==0.9.1) ; extra == 'fasttext'
Provides-Extra: onnx
Requires-Dist: onnxruntime ; extra == 'onnx'
